{"ongoing_trials": {}, "hyperparameters": {"space": [{"class_name": "Int", "config": {"name": "num_layers", "default": null, "conditions": [], "min_value": 1, "max_value": 3, "step": 1, "sampling": null}}, {"class_name": "Int", "config": {"name": "units_0", "default": null, "conditions": [], "min_value": 32, "max_value": 512, "step": 32, "sampling": null}}, {"class_name": "Choice", "config": {"name": "activation", "default": "relu", "conditions": [], "values": ["relu", "tanh", "sigmoid", "selu"], "ordered": false}}, {"class_name": "Boolean", "config": {"name": "dropout", "default": false, "conditions": []}}, {"class_name": "Float", "config": {"name": "learning_rate", "default": 0.0001, "conditions": [], "min_value": 0.0001, "max_value": 0.01, "step": null, "sampling": "log"}}, {"class_name": "Int", "config": {"name": "units_1", "default": null, "conditions": [], "min_value": 32, "max_value": 512, "step": 32, "sampling": null}}, {"class_name": "Int", "config": {"name": "units_2", "default": null, "conditions": [], "min_value": 32, "max_value": 512, "step": 32, "sampling": null}}], "values": {"num_layers": 1, "units_0": 32, "activation": "relu", "dropout": false, "learning_rate": 0.0001, "units_1": 32, "units_2": 32}}, "seed": 6136, "seed_state": 6155, "tried_so_far": ["d2b3e63d173ecde51e17716e15422e45", "c8412063927ec10baf0e6de4a985d5d9", "c2e141876dd4ece908908a50b9d03d45"]}